{"cameraMode":{"drawMode":0,"name":"Shaded","section":"Shading Mode"},"sceneLighting":true,"audioPlay":false,"sceneViewState":{"m_AlwaysRefresh":false,"showFog":true,"showSkybox":true,"showFlares":true,"showImageEffects":true,"showParticleSystems":true,"showVisualEffectGraphs":true,"m_FxEnabled":true},"in2DMode":false,"pivot":{"x":169.49261474609376,"y":-147.19866943359376,"z":-262.8023681640625},"rotation":{"x":0.06937526911497116,"y":0.927463710308075,"z":-0.21643947064876557,"w":0.29807132482528689},"size":173.0361785888672,"orthographic":false}